phyjax2d/__init__.py
phyjax2d/impl.py
phyjax2d/moderngl_vis.py
phyjax2d/raycast.py
phyjax2d/utils.py
phyjax2d/vec2d.py
phyjax2d-0.3.3.dist-info/licenses/LICENSE
phyjax2d-0.3.3.dist-info/METADATA
phyjax2d-0.3.3.dist-info/WHEEL
phyjax2d-0.3.3.dist-info/top_level.txt
phyjax2d-0.3.3.dist-info/RECORD
